setup.cfg
setup.py
epoxy/__init__.py
epoxy/registry.py
epoxy/bases/__init__.py
epoxy/bases/class_type_creator.py
epoxy/bases/input_type.py
epoxy/bases/mutation.py
epoxy/bases/object_type.py
epoxy/bases/scalar.py
epoxy/contrib/__init__.py
epoxy/contrib/relay/__init__.py
epoxy/contrib/relay/mixin.py
epoxy/contrib/relay/utils.py
epoxy/contrib/relay/connections/__init__.py
epoxy/contrib/relay/connections/cursor.py
epoxy/contrib/relay/connections/sorted_collection.py
epoxy/contrib/relay/data_source/__init__.py
epoxy/contrib/relay/data_source/base.py
epoxy/contrib/relay/data_source/memory.py
epoxy/contrib/relay/metaclasses/__init__.py
epoxy/contrib/relay/metaclasses/mutation.py
epoxy/metaclasses/__init__.py
epoxy/metaclasses/input_type.py
epoxy/metaclasses/interface.py
epoxy/metaclasses/mutation.py
epoxy/metaclasses/object_type.py
epoxy/metaclasses/scalar.py
epoxy/metaclasses/union.py
epoxy/types/__init__.py
epoxy/types/argument.py
epoxy/types/field.py
epoxy/utils/__init__.py
epoxy/utils/enum_to_graphql_enum.py
epoxy/utils/first_of.py
epoxy/utils/gen_id.py
epoxy/utils/get_declared_fields.py
epoxy/utils/make_default_resolver.py
epoxy/utils/maybe_callable.py
epoxy/utils/maybe_t.py
epoxy/utils/method_dispatch.py
epoxy/utils/no_implementation_registration.py
epoxy/utils/thunk.py
epoxy/utils/to_camel_case.py
epoxy/utils/weak_ref_holder.py
epoxy/utils/wrap_resolver_translating_arguments.py
epoxy/utils/yank_potential_fields.py
graphql_epoxy.egg-info/PKG-INFO
graphql_epoxy.egg-info/SOURCES.txt
graphql_epoxy.egg-info/dependency_links.txt
graphql_epoxy.egg-info/requires.txt
graphql_epoxy.egg-info/top_level.txt
tests/test_relay/__init__.py
tests/test_relay/test_relay_connections.py
tests/test_relay/test_relay_mutation.py
tests/test_relay/test_relay_node.py
tests/test_starwars/__init__.py
tests/test_starwars/data.py
tests/test_starwars/schema.py
tests/test_starwars/test_query.py